[
  {
    "id": 0,
    "cot": "",
    "final_answer": ""
  },
  {
    "id": 1,
    "cot": "",
    "final_answer": ""
  },
  {
    "id": 2,
    "cot": "",
    "final_answer": ""
  },
  {
    "id": 3,
    "cot": "",
    "final_answer": ""
  },
  {
    "id": 4,
    "cot": "",
    "final_answer": ""
  },
  {
    "id": 5,
    "cot": "",
    "final_answer": ""
  },
  {
    "id": 6,
    "cot": "",
    "final_answer": ""
  },
  {
    "id": 7,
    "cot": "",
    "final_answer": ""
  },
  {
    "id": 8,
    "cot": "",
    "final_answer": ""
  },
  {
    "id": 9,
    "cot": "",
    "final_answer": ""
  },
  {
    "id": 10,
    "cot": "",
    "final_answer": ""
  },
  {
    "id": 11,
    "cot": "",
    "final_answer": ""
  },
  {
    "id": 12,
    "cot": "",
    "final_answer": ""
  },
  {
    "id": 13,
    "cot": "",
    "final_answer": ""
  },
  {
    "id": 14,
    "cot": "",
    "final_answer": ""
  },
  {
    "id": 15,
    "cot": "",
    "final_answer": ""
  },
  {
    "id": 16,
    "cot": "",
    "final_answer": ""
  },
  {
    "id": 17,
    "cot": "",
    "final_answer": ""
  },
  {
    "id": 18,
    "cot": "",
    "final_answer": ""
  },
  {
    "id": 19,
    "cot": "",
    "final_answer": ""
  }
]